sonolus/__init__.py
sonolus/py.typed
sonolus/backend/__init__.py
sonolus/backend/blocks.py
sonolus/backend/excepthook.py
sonolus/backend/finalize.py
sonolus/backend/interpret.py
sonolus/backend/ir.py
sonolus/backend/mode.py
sonolus/backend/node.py
sonolus/backend/ops.py
sonolus/backend/place.py
sonolus/backend/utils.py
sonolus/backend/visitor.py
sonolus/backend/optimize/__init__.py
sonolus/backend/optimize/allocate.py
sonolus/backend/optimize/constant_evaluation.py
sonolus/backend/optimize/copy_coalesce.py
sonolus/backend/optimize/dead_code.py
sonolus/backend/optimize/dominance.py
sonolus/backend/optimize/flow.py
sonolus/backend/optimize/inlining.py
sonolus/backend/optimize/liveness.py
sonolus/backend/optimize/optimize.py
sonolus/backend/optimize/passes.py
sonolus/backend/optimize/simplify.py
sonolus/backend/optimize/ssa.py
sonolus/build/__init__.py
sonolus/build/cli.py
sonolus/build/collection.py
sonolus/build/compile.py
sonolus/build/dev_server.py
sonolus/build/engine.py
sonolus/build/level.py
sonolus/build/node.py
sonolus/build/project.py
sonolus/script/__init__.py
sonolus/script/archetype.py
sonolus/script/array.py
sonolus/script/array_like.py
sonolus/script/bucket.py
sonolus/script/containers.py
sonolus/script/debug.py
sonolus/script/easing.py
sonolus/script/effect.py
sonolus/script/engine.py
sonolus/script/globals.py
sonolus/script/instruction.py
sonolus/script/interval.py
sonolus/script/iterator.py
sonolus/script/level.py
sonolus/script/maybe.py
sonolus/script/metadata.py
sonolus/script/num.py
sonolus/script/options.py
sonolus/script/particle.py
sonolus/script/pointer.py
sonolus/script/printing.py
sonolus/script/project.py
sonolus/script/quad.py
sonolus/script/record.py
sonolus/script/runtime.py
sonolus/script/sprite.py
sonolus/script/stream.py
sonolus/script/text.py
sonolus/script/timing.py
sonolus/script/transform.py
sonolus/script/ui.py
sonolus/script/values.py
sonolus/script/vec.py
sonolus/script/internal/__init__.py
sonolus_py-0.12.5.dist-info/METADATA
sonolus_py-0.12.5.dist-info/WHEEL
sonolus_py-0.12.5.dist-info/entry_points.txt
sonolus_py-0.12.5.dist-info/licenses/LICENSE
sonolus_py-0.12.5.dist-info/RECORD
