Metadata-Version: 2.4
Name: sonolus.py
Version: 0.12.5
Summary: Sonolus engine development in Python
Project-URL: Documentation, https://sonolus.py.qwewqa.xyz/
Project-URL: Repository, https://github.com/qwewqa/sonolus.py
Project-URL: Issues, https://github.com/qwewqa/sonolus.py/issues
Project-URL: Changelog, https://sonolus.py.qwewqa.xyz/changelog/
License-File: LICENSE
Requires-Python: >=3.12.5
